[
    {
        "username": "elonmusk",
        "id": "1770812308064752050",
        "created_on": "2024-03-21T13:58:49+00:00",
        "text": "And, although it shouldn\u2019t need to said, I believe in the Constitution and freedom of speech",
        "likes": "7372",
        "url": "https://twitter.com/elonmusk/status/1770812308064752050"
    },
    {
        "username": "elonmusk",
        "id": "1770803933503508774",
        "created_on": "2024-03-21T13:25:32+00:00",
        "text": "\ud83c\udfaf",
        "likes": "11630",
        "url": "https://twitter.com/elonmusk/status/1770803933503508774"
    },
    {
        "username": "elonmusk",
        "id": "1770802773547770345",
        "created_on": "2024-03-21T13:20:55+00:00",
        "text": "Google is deeply infected with the woke mind virus",
        "likes": "54639",
        "url": "https://twitter.com/elonmusk/status/1770802773547770345"
    },
    {
        "username": "elonmusk",
        "id": "1770800804863037622",
        "created_on": "2024-03-21T13:13:06+00:00",
        "text": "The New York Times is pure propaganda",
        "likes": "43525",
        "url": "https://twitter.com/elonmusk/status/1770800804863037622"
    },
    {
        "username": "elonmusk",
        "id": "1770703987152458046",
        "created_on": "2024-03-21T06:48:23+00:00",
        "text": "How committed is the Biden administration to an open border? It took the Supreme Court overruling White House objections to allow Texas to enforce immigration law. \n\n https://t.co/CGVMvCWmmZ",
        "likes": "0",
        "url": "https://twitter.com/elonmusk/status/1770703987152458046"
    },
    {
        "username": "elonmusk",
        "id": "1770575265716146280",
        "created_on": "2024-03-20T22:16:53+00:00",
        "text": "\ud835\udd4f in numbers!  \ud83d\ude80",
        "likes": "0",
        "url": "https://twitter.com/elonmusk/status/1770575265716146280"
    },
    {
        "username": "elonmusk",
        "id": "1770360871338033613",
        "created_on": "2024-03-20T08:04:58+00:00",
        "text": "Right now, the Supreme Court is hearing a big free speech case:\nhttps://t.co/1O9dP3piCo\n\nA lower court ruled that the Biden admin violated the 1st Amendment, as it pressured companies to censor news about Hunter's laptop, Covid, and more.\n\nTRUE things were censored, like: https://t.co/ROsrZKZuW4",
        "likes": "0",
        "url": "https://twitter.com/elonmusk/status/1770360871338033613"
    },
    {
        "username": "elonmusk",
        "id": "1770232706657653071",
        "created_on": "2024-03-19T23:35:41+00:00",
        "text": "https://t.co/PwikoVKONw",
        "likes": "637315",
        "url": "https://twitter.com/elonmusk/status/1770232706657653071"
    },
    {
        "username": "elonmusk",
        "id": "1770224558664241661",
        "created_on": "2024-03-19T23:03:18+00:00",
        "text": "Teams test the new emergency chutes from the pad 40 crew tower in Florida https://t.co/rWVj7zaHp0",
        "likes": "0",
        "url": "https://twitter.com/elonmusk/status/1770224558664241661"
    },
    {
        "username": "elonmusk",
        "id": "1770224502703882509",
        "created_on": "2024-03-19T23:03:05+00:00",
        "text": "Dragon is now operational on 2 launchpads!",
        "likes": "90599",
        "url": "https://twitter.com/elonmusk/status/1770224502703882509"
    },
    {
        "username": "elonmusk",
        "id": "1770222178279252062",
        "created_on": "2024-03-19T22:53:51+00:00",
        "text": "\ud83c\udf4a is the new \ud83c\udf4b",
        "likes": "111996",
        "url": "https://twitter.com/elonmusk/status/1770222178279252062"
    },
    {
        "username": "elonmusk",
        "id": "1770201933074104538",
        "created_on": "2024-03-19T21:33:24+00:00",
        "text": ".@steveaoki just received his Cybertruck\n https://t.co/bJv7LEqQI3",
        "likes": "203012",
        "url": "https://twitter.com/elonmusk/status/1770201933074104538"
    },
    {
        "username": "elonmusk",
        "id": "1770181321018478622",
        "created_on": "2024-03-19T20:11:29+00:00",
        "text": "BREAKING: \ud835\udd4f has paid more than $45 million to over 150,000 creators on the platform.\n\n https://t.co/oJWoVPVchV",
        "likes": "0",
        "url": "https://twitter.com/elonmusk/status/1770181321018478622"
    },
    {
        "username": "elonmusk",
        "id": "1770178094172602792",
        "created_on": "2024-03-19T19:58:40+00:00",
        "text": "As always, I say this as an immigrant who is proud to have become a citizen and who supports expanded and expedited *legal* immigration",
        "likes": "22703",
        "url": "https://twitter.com/elonmusk/status/1770178094172602792"
    },
    {
        "username": "elonmusk",
        "id": "1770171578736627997",
        "created_on": "2024-03-19T19:32:47+00:00",
        "text": "Most reasonable people, because they are reasonable, cannot believe that the goal of the far left is to end America \n https://t.co/7TchRPGU1l",
        "likes": "196431",
        "url": "https://twitter.com/elonmusk/status/1770171578736627997"
    }
]